mypackage/__init__.py
mypackage/main.py
simplereader-0.0.3.dist-info/LICENSE
simplereader-0.0.3.dist-info/METADATA
simplereader-0.0.3.dist-info/WHEEL
simplereader-0.0.3.dist-info/top_level.txt
simplereader-0.0.3.dist-info/RECORD
